{
  "version": "https://jsonfeed.org/version/1.1",
  "title": "200 Acres Honey",
  "language": "en",
  "home_page_url": "https://example.com",
  "feed_url": "https://example.com/feed/en.feed.json",
  "description": "TODO",
  "author": {
    "name": "John Smithson",
    "url": "https://example.com"
  },
  "items": [{
      "id": "https://example.com/11ty-starter/posts/en/first/",
      "url": "https://example.com/11ty-starter/posts/en/first/",
      "title": "Why 200 Acres",
      "content_html": "<p>The name 200 acres was inspired by the Location of the bee hives on the edge of the Stray in Harrogate North Yorkshire. The stray is an historic allotment of 200 acres for public use.</p>\n<p><img src=\"/static/stray-blossom.png\" alt=\"Cherry blossom on teh stray, Harrogate North Yorkshire\" title=\"Blossom on the Stray\"></p>\n<p>In Spring the Stray puts on a wonderful show.</p>\n",
      "date_published": "2022-06-01T00:00:00Z"
    },{
      "id": "https://example.com/11ty-starter/posts/en/second/",
      "url": "https://example.com/11ty-starter/posts/en/second/",
      "title": "Swarm season",
      "content_html": "<p>Swarm season is upon us, this time generally begins in April in the UK and continues until the bees start to shut down for the winter.</p>\n<p>A swarm is the bees method of reproducing, whereby a new queen is born and the old queen leaves with a portion of the hive’s population to start a new colony away from home.</p>\n<p><img src=\"/static/bee-swarm.png\" alt=\"A swarm of bees resting on a branch\" title=\"A swarm of bees\"></p>\n<p>With a reference later in the document defining the URL location:</p>\n",
      "date_published": "2022-04-01T00:00:00Z"
    }
  ]
}
